{
  "image_name": "D05_240929_AM_IMG_7629_12",
  "image_path": "../data/experiments/validation_test/datasets/cot/1. test_image/wrap/D05_240929_AM_IMG_7629_12.jpg",
  "time": "2025-08-06 20:36:26",
  "summary": {
    "ori_txt": "송도 1공구아파트 및 단지내상가 포스코 자사고 앞 파격 조건 분양",
    "ban_cls": "민간 현수막",
    "reason": "현수막에는 상업 광고와 상점/개인 목적 문구가 포함되어 있어 민간 현수막으로 분류되었습니다."
  },
  "vlm_raw": "- 현수막 내용 : 송도 1공구아파트 및 단지내상가 포스코 자사고 앞 파격 조건 분양\n- 분류 결과: 민간 현수막\n- 판단 이유: 현수막에는 상업 광고와 상점/개인 목적 문구가 포함되어 있어 민간 현수막으로 분류되었습니다."
}